pcapng/__init__.py
pcapng/block.py
pcapng/block_test.py
pcapng/codec.py
pcapng/const.py
pcapng/linktype.py
pcapng/mrt.py
pcapng/mrt_test.py
pcapng/option.py
pcapng/option_test.py
pcapng/pen.py
pcapng/tlv.py
pcapng/tlv_test.py
pcapng/util.py
pcapng/util_test.py
pcapng-0.1.25.dist-info/LICENSE.txt
pcapng-0.1.25.dist-info/METADATA
pcapng-0.1.25.dist-info/WHEEL
pcapng-0.1.25.dist-info/top_level.txt
pcapng-0.1.25.dist-info/RECORD
