Metadata-Version: 2.1
Name: pcapng
Version: 0.1.25
Summary: Tool for reading/writing PCAPNG network packet capture files.
Home-page: https://github.com/cloojure/pcapng
Author: Alan Thompson
Author-email: athomps@brocade.com
License: Apache
Keywords: pcapng pcap networking monitoring
Platform: UNKNOWN
Classifier: Development Status :: 3 - Alpha
Classifier: Intended Audience :: Developers
Classifier: Topic :: System :: Networking
Classifier: License :: OSI Approved :: Apache Software License
Classifier: Programming Language :: Python :: 2.7
Provides-Extra: dev
Provides-Extra: test
